flask_header_session/__init__.py
flask_header_session/sessions.py
Flask_Header_Session-0.0.7.dist-info/LICENSE
Flask_Header_Session-0.0.7.dist-info/METADATA
Flask_Header_Session-0.0.7.dist-info/WHEEL
Flask_Header_Session-0.0.7.dist-info/top_level.txt
Flask_Header_Session-0.0.7.dist-info/RECORD
