Metadata-Version: 2.1
Name: Flask-Header-Session
Version: 0.0.7
Summary: Flask server side session via HTTP header
Home-page: https://github.com/laalaguer/flask-session
Author: Xiqing Chu
Author-email: laalaguer@gmail.com
License: BSD
Platform: any
Classifier: Environment :: Web Environment
Classifier: Intended Audience :: Developers
Classifier: License :: OSI Approved :: BSD License
Classifier: Operating System :: OS Independent
Classifier: Programming Language :: Python :: 2
Classifier: Programming Language :: Python :: 3
Classifier: Topic :: Internet :: WWW/HTTP :: Dynamic Content
Classifier: Topic :: Software Development :: Libraries :: Python Modules
Requires-Dist: Flask (>=0.8)
